{
    "schema_version": 2,
    "oldId": "-LEHbc48JHyvR6jIracl",
    "name": "Glaephclaw - Prime Jarlbane",
    "avatar": "https://5etools.com/img/MM/White Dragon Wyrmling.png",
    "bio": "%3Cdiv%20class%3D%22userscript-%20userscript-statsInlineHead%22%3E%3Cp%3EThe%20smallest%2C%20least%20intelligent%2C%20and%20most%20animalistic%20of%20the%20chromatic%20dragons%2C%20white%20dragons%20dwell%20in%20frigid%20climes%2C%20favoring%20arctic%20areas%20or%20icy%20mountains.%20They%20are%20vicious%2C%20cruel%20reptiles%20driven%20by%20hunger%20and%20greed.%3C/p%3E%3Cp%3EA%20white%20dragon%20has%20feral%20eyes%2C%20a%20sleek%20profile%2C%20and%20a%20spined%20crest.%20The%20scales%20of%20a%20wyrmling%20white%20dragon%20glisten%20pure%20white.%20As%20the%20dragon%20ages%2C%20its%20sheen%20disappears%20and%20some%20of%20its%20scales%20begin%20to%20darken%2C%20so%20that%20by%20the%20time%20it%20is%20old%2C%20it%20is%20mottled%20by%20patches%20of%20pale%20blue%20and%20light%20gray.%20This%20patterning%20helps%20the%20dragon%20blend%20into%20the%20realms%20of%20ice%20and%20stone%20in%20which%20it%20hunts%2C%20and%20to%20fade%20from%20view%20when%20it%20soars%20across%20a%20cloud-filled%20sky.%3C/p%3E%3Cp%3EPrimal%20and%20Vengeful.%20White%20dragons%20lack%20the%20cunning%20and%20tactics%20of%20most%20other%20dragons.%20However%2C%20their%20bestial%20nature%20makes%20them%20the%20best%20hunters%20among%20all%20dragonkind%2C%20singularly%20focused%20on%20surviving%20and%20slaughtering%20their%20enemies.%20A%20white%20dragon%20consumes%20only%20food%20that%20has%20been%20frozen%2C%20devouring%20creatures%20killed%20by%20its%20breath%20weapon%20while%20they%20are%20still%20stiff%20and%20frigid.%20It%20encases%20other%20kills%20in%20ice%20or%20buries%20them%20in%20snow%20near%20its%20lair%2C%20and%20finding%20such%20a%20larder%20is%20a%20good%20indication%20that%20a%20white%20dragon%20dwells%20nearby.%3C/p%3E%3Cp%3EA%20white%20dragon%20also%20keeps%20the%20bodies%20of%20its%20greatest%20enemies%20as%20trophies%2C%20freezing%20corpses%20where%20it%20can%20look%20upon%20them%20and%20gloat.%20The%20remains%20of%20giants%2C%20remorhazes%2C%20and%20other%20dragons%20are%20often%20positioned%20prominently%20within%20a%20white%20dragon%27s%20lair%20as%20warnings%20to%20intruders.%3C/p%3E%3Cp%3EThough%20only%20moderately%20intelligent%2C%20white%20dragons%20have%20extraordinary%20memories.%20They%20recall%20every%20slight%20and%20defeat%2C%20and%20have%20been%20known%20to%20conduct%20malicious%20vendettas%20against%20creatures%20that%20have%20offended%20them.%20This%20often%20includes%20silver%20dragons%2C%20which%20lair%20in%20the%20same%20territories%20as%20whites.%20White%20dragons%20can%20speak%20as%20all%20dragons%20can%2C%20but%20they%20rarely%20talk%20unless%20moved%20to%20do%20so.%3C/p%3E%3Cp%3ELone%20Masters.%20White%20dragons%20avoid%20all%20other%20dragons%20except%20whites%20of%20the%20opposite%20sex.%20Even%20then%2C%20when%20white%20dragons%20seek%20each%20other%20out%20as%20mates%2C%20they%20stay%20together%20only%20long%20enough%20to%20conceive%20offspring%20before%20fleeing%20into%20isolation%20again.%3C/p%3E%3Cp%3EWhite%20dragons%20can%27t%20abide%20rivals%20near%20their%20lairs.%20As%20a%20result%2C%20a%20white%20dragon%20attacks%20other%20creatures%20without%20provocation%2C%20viewing%20such%20creatures%20as%20either%20too%20weak%20or%20too%20powerful%20to%20live.%20The%20only%20creatures%20that%20typically%20serve%20a%20white%20dragon%20are%20intelligent%20humanoids%20that%20demonstrate%20enough%20strength%20to%20assuage%20the%20dragon%27s%20wrath%2C%20and%20can%20put%20up%20with%20sustaining%20regular%20losses%20as%20a%20result%20of%20its%20hunger.%20This%20includes%20dragon-worshiping%20kobolds%2C%20which%20are%20commonly%20found%20in%20their%20lairs.%3C/p%3E%3Cp%3EPowerful%20creatures%20can%20sometimes%20gain%20a%20white%20dragon%27s%20obedience%20through%20a%20demonstration%20of%20physical%20or%20magical%20might.%20Frost%20giants%20challenge%20white%20dragons%20to%20prove%20their%20own%20strength%20and%20improve%20their%20status%20in%20their%20clans%2C%20and%20their%20cracked%20bones%20litter%20many%20a%20white%20dragon%27s%20lair.%20However%2C%20a%20white%20dragon%20defeated%20by%20a%20frost%20giant%20often%20becomes%20its%20servant%2C%20accepting%20the%20mastery%20of%20a%20superior%20creature%20in%20exchange%20for%20asserting%20its%20own%20domination%20over%20the%20other%20creatures%20that%20serve%20or%20oppose%20the%20giant.%3C/p%3E%3Cp%3ETreasure%20Under%20Ice.%20White%20dragons%20love%20the%20cold%20sparkle%20of%20ice%20and%20favor%20treasure%20with%20similar%20qualities%2C%20particularly%20diamonds.%20However%2C%20in%20their%20remote%20arctic%20climes%2C%20the%20treasure%20hoards%20of%20white%20dragons%20more%20often%20contain%20walrus%20and%20mammoth%20tusk%20ivory%2C%20whale-bone%20sculptures%2C%20figureheads%20from%20ships%2C%20furs%2C%20and%20magic%20items%20seized%20from%20overly%20bold%20adventurers.%3C/p%3E%3Cp%3ELoose%20coins%20and%20gems%20are%20spread%20across%20a%20white%20dragon%27s%20lair%2C%20glittering%20like%20stars%20when%20the%20light%20strikes%20them.%20Larger%20treasures%20and%20chests%20are%20encased%20in%20layers%20of%20rime%20created%20by%20the%20white%20dragon%27s%20breath%2C%20and%20held%20safe%20beneath%20layers%20of%20transparent%20ice.%20The%20dragon%27s%20great%20strength%20allows%20it%20to%20easily%20access%20its%20wealth%2C%20while%20lesser%20creatures%20must%20spend%20hours%20chipping%20away%20or%20melting%20the%20ice%20to%20reach%20the%20dragon%27s%20main%20hoard.%3C/p%3E%3Cp%3EA%20white%20dragon%27s%20flawless%20memory%20means%20that%20it%20knows%20how%20it%20came%20to%20possess%20every%20coin%2C%20gem%2C%20and%20magic%20item%20in%20its%20hoard%2C%20and%20it%20associates%20each%20item%20with%20a%20specific%20victory.%20White%20dragons%20are%20notoriously%20difficult%20to%20bribe%2C%20since%20any%20offers%20of%20treasure%20are%20seen%20as%20an%20insult%20to%20their%20ability%20to%20simply%20slay%20the%20creature%20making%20the%20offer%20and%20seize%20the%20treasure%20on%20their%20own.%3C/p%3E%3Cdiv%20class%3D%22userscript-%20userscript-statsInlineHead%22%3E%3Cspan%20class%3D%22userscript-entry-title%22%3EA%20White%20Dragon%27s%20Lair.%3C/span%3E%20%3Cp%3EWhite%20dragons%20lair%20in%20icy%20caves%20and%20deep%20subterranean%20chambers%20far%20from%20the%20sun.%20They%20favor%20high%20mountain%20vales%20accessible%20only%20by%20flying%2C%20caverns%20in%20cliff%20faces%2C%20and%20labyrinthine%20ice%20caves%20in%20glaciers.%20White%20dragons%20love%20vertical%20heights%20in%20their%20caverns%2C%20flying%20up%20to%20the%20ceiling%20to%20latch%20on%20like%20bats%20or%20slithering%20down%20icy%20crevasses.%3C/p%3E%3Cp%3EA%20legendary%20white%20dragon%27s%20innate%20magic%20deepens%20the%20cold%20in%20the%20area%20around%20its%20lair.%20Mountain%20caverns%20are%20fast%20frozen%20by%20the%20white%20dragon%27s%20presence.%20A%20white%20dragon%20can%20often%20detect%20intruders%20by%20the%20way%20the%20keening%20wind%20in%20its%20lair%20changes%20tone.%3C/p%3E%3Cp%3EA%20white%20dragon%20rests%20on%20high%20ice%20shelves%20and%20cliffs%20in%20its%20lair%2C%20the%20floor%20around%20it%20a%20treacherous%20morass%20of%20broken%20ice%20and%20stone%2C%20hidden%20pits%2C%20and%20slippery%20slopes.%20As%20foes%20struggle%20to%20move%20toward%20it%2C%20the%20dragon%20flies%20from%20perch%20to%20perch%20and%20destroys%20them%20with%20its%20freezing%20breath.%3C/p%3E%3C/div%3E%3Cdiv%20class%3D%22userscript-%20userscript-statsInlineHead%22%3E%3Cspan%20class%3D%22userscript-entry-title%22%3ERegional%20Effects.%3C/span%3E%20%3Cp%3EThe%20region%20containing%20a%20legendary%20white%20dragon%27s%20lair%20is%20warped%20by%20the%20dragon%27s%20magic%2C%20which%20creates%20one%20or%20more%20of%20the%20following%20effects%3A%3C/p%3E%3Cul%3E%3Cli%3EChilly%20fog%20lightly%20obscures%20the%20land%20within%206%20miles%20of%20the%20dragon%27s%20lair.%3C/li%3E%3Cli%3EFreezing%20precipitation%20falls%20within%206%20miles%20of%20the%20dragon%27s%20lair%2C%20sometimes%20forming%20blizzard%20conditions%20when%20the%20dragon%20is%20at%20rest.%3C/li%3E%3Cli%3EIcy%20walls%20block%20off%20areas%20in%20the%20dragon%27s%20lair.%20Each%20wall%20is%206%20inches%20thick%2C%20and%20a%2010-foot%20section%20has%20AC%205%2C%2015%20hit%20points%2C%20vulnerability%20to%20fire%20damage%2C%20and%20immunity%20to%20acid%2C%20cold%2C%20necrotic%2C%20poison%2C%20and%20psychic%20damage.%20If%20the%20dragon%20wishes%20to%20move%20through%20a%20wall%2C%20it%20can%20do%20so%20without%20slowing%20down.%20The%20portion%20of%20the%20wall%20the%20dragon%20moves%20through%20is%20destroyed%2C%20however.%3C/li%3E%3C/ul%3E%3Cp%3EIf%20the%20dragon%20dies%2C%20the%20fog%20and%20precipitation%20fade%20within%201%20day.%20The%20ice%20walls%20melt%20over%20the%20course%20of%201d10%20days.%3C/p%3E%3C/div%3E%3Cdiv%20class%3D%22userscript-%20userscript-statsInlineHead%22%3E%3Cspan%20class%3D%22userscript-entry-title%22%3EDragons.%3C/span%3E%20%3Cp%3ETrue%20dragons%20are%20winged%20reptiles%20of%20ancient%20lineage%20and%20fearsome%20power.%20They%20are%20known%20and%20feared%20for%20their%20predatory%20cunning%20and%20greed%2C%20with%20the%20oldest%20dragons%20accounted%20as%20some%20of%20the%20most%20powerful%20creatures%20in%20the%20world.%20Dragons%20are%20also%20magical%20creatures%20whose%20innate%20power%20fuels%20their%20dreaded%20breath%20weapons%20and%20other%20preternatural%20abilities.%3C/p%3E%3Cp%3EMany%20creatures%2C%20including%20wyverns%20and%20dragon%20turtles%2C%20have%20draconic%20blood.%20However%2C%20true%20dragons%20fall%20into%20the%20two%20broad%20categories%20of%20chromatic%20and%20metallic%20dragons.%20The%20black%2C%20blue%2C%20green%2C%20red%2C%20and%20white%20dragons%20are%20selfish%2C%20evil%2C%20and%20feared%20by%20all.%20The%20brass%2C%20bronze%2C%20copper%2C%20gold%2C%20and%20silver%20dragons%20are%20noble%2C%20good%2C%20and%20highly%20respected%20by%20the%20wise.%3C/p%3E%3Cp%3EThough%20their%20goals%20and%20ideals%20vary%20tremendously%2C%20all%20true%20dragons%20covet%20wealth%2C%20hoarding%20mounds%20of%20coins%20and%20gathering%20gems%2C%20jewels%2C%20and%20magic%20items.%20Dragons%20with%20large%20hoards%20are%20loath%20to%20leave%20them%20for%20long%2C%20venturing%20out%20of%20their%20lairs%20only%20to%20patrol%20or%20feed.%3C/p%3E%3Cp%3ETrue%20dragons%20pass%20through%20four%20distinct%20stages%20of%20life%2C%20from%20lowly%20wyrmlings%20to%20ancient%20dragons%2C%20which%20can%20live%20for%20over%20a%20thousand%20years.%20In%20that%20time%2C%20their%20might%20can%20become%20unrivaled%20and%20their%20hoards%20can%20grow%20beyond%20price.%3C/p%3E%3Cp%3EDragon%20Age%20Categories%3C/p%3E%3Ctable%20class%3D%22userscript-striped-odd%22%3E%3Ccaption%3E%3C/caption%3E%3Cthead%3E%3Ctr%3E%3Cth%20class%3D%22userscript-col-xs-4%22%3ECategory%3C/th%3E%3Cth%20class%3D%22userscript-col-xs-4%22%3ESize%3C/th%3E%3Cth%20class%3D%22userscript-col-xs-4%22%3EAge%20Range%3C/th%3E%3C/tr%3E%3C/thead%3E%3Ctbody%3E%3Ctr%3E%3Ctd%20class%3D%22userscript-col-xs-4%22%3EWyrmling%3C/td%3E%3Ctd%20class%3D%22userscript-col-xs-4%22%3EMedium%3C/td%3E%3Ctd%20class%3D%22userscript-col-xs-4%22%3E5%20years%20or%20less%3C/td%3E%3C/tr%3E%3Ctr%3E%3Ctd%20class%3D%22userscript-col-xs-4%22%3EYoung%3C/td%3E%3Ctd%20class%3D%22userscript-col-xs-4%22%3ELarge%3C/td%3E%3Ctd%20class%3D%22userscript-col-xs-4%22%3E6-100%20years%3C/td%3E%3C/tr%3E%3Ctr%3E%3Ctd%20class%3D%22userscript-col-xs-4%22%3EAdult%3C/td%3E%3Ctd%20class%3D%22userscript-col-xs-4%22%3EHuge%3C/td%3E%3Ctd%20class%3D%22userscript-col-xs-4%22%3E101-800%20years%3C/td%3E%3C/tr%3E%3Ctr%3E%3Ctd%20class%3D%22userscript-col-xs-4%22%3EAncient%3C/td%3E%3Ctd%20class%3D%22userscript-col-xs-4%22%3EGargantuan%3C/td%3E%3Ctd%20class%3D%22userscript-col-xs-4%22%3E801%20years%20or%20more%3C/td%3E%3C/tr%3E%3C/tbody%3E%3C/table%3E%3C/div%3E%3Cdiv%20class%3D%22userscript-%20userscript-statsInlineHead%22%3E%3Cspan%20class%3D%22userscript-entry-title%22%3EChromatic%20Dragons.%3C/span%3E%20%3Cp%3EThe%20black%2C%20blue%2C%20green%2C%20red%2C%20and%20white%20dragons%20represent%20the%20evil%20side%20of%20dragonkind.%20Aggressive%2C%20gluttonous%2C%20and%20vain%2C%20chromatic%20dragons%20are%20dark%20sages%20and%20powerful%20tyrants%20feared%20by%20all%20creatures-including%20each%20other.%3C/p%3E%3Cp%3EDriven%20by%20Greed.%20Chromatic%20dragons%20lust%20after%20treasure%2C%20and%20this%20greed%20colors%20their%20every%20scheme%20and%20plot.%20They%20believe%20that%20the%20world%27s%20wealth%20belongs%20to%20them%20by%20right%2C%20and%20a%20chromatic%20dragon%20seizes%20that%20wealth%20without%20regard%20for%20the%20humanoids%20and%20other%20creatures%20that%20have%20%22stolen%22%20it.%20With%20its%20piles%20of%20coins%2C%20gleaming%20gems%2C%20and%20magic%20items%2C%20a%20dragon%27s%20hoard%20is%20the%20stuff%20of%20legend.%20However%2C%20chromatic%20dragons%20have%20no%20interest%20in%20commerce%2C%20amassing%20wealth%20for%20no%20other%20reason%20than%20to%20have%20it.%3C/p%3E%3Cp%3ECreatures%20of%20Ego.%20Chromatic%20dragons%20are%20united%20by%20their%20sense%20of%20superiority%2C%20believing%20themselves%20the%20most%20powerful%20and%20worthy%20of%20all%20mortal%20creatures.%20When%20they%20interact%20with%20other%20creatures%2C%20it%20is%20only%20to%20further%20their%20own%20interests.%20They%20believe%20in%20their%20innate%20right%20to%20rule%2C%20and%20this%20belief%20is%20the%20cornerstone%20of%20every%20chromatic%20dragon%27s%20personality%20and%20worldview.%20Trying%20to%20humble%20a%20chromatic%20dragon%20is%20like%20trying%20to%20convince%20the%20wind%20to%20stop%20blowing.%20To%20these%20creatures%2C%20humanoids%20are%20animals%2C%20fit%20to%20serve%20as%20prey%20or%20beasts%20of%20burden%2C%20and%20wholly%20unworthy%20of%20respect.%3C/p%3E%3Cp%3EDangerous%20Lairs.%20A%20dragon%27s%20lair%20serves%20as%20the%20seat%20of%20its%20power%20and%20a%20vault%20for%20its%20treasure.%20With%20its%20innate%20toughness%20and%20tolerance%20for%20severe%20environmental%20effects%2C%20a%20dragon%20selects%20or%20builds%20a%20lair%20not%20for%20shelter%20but%20for%20defense%2C%20favoring%20multiple%20entrances%20and%20exits%2C%20and%20security%20for%20its%20hoard.%3C/p%3E%3Cp%3EMost%20chromatic%20dragon%20lairs%20are%20hidden%20in%20dangerous%20and%20remote%20locations%20to%20prevent%20all%20but%20the%20most%20audacious%20mortals%20from%20reaching%20them.%20A%20black%20dragon%20might%20lair%20in%20the%20heart%20of%20a%20vast%20swamp%2C%20while%20a%20red%20dragon%20might%20claim%20the%20caldera%20of%20an%20active%20volcano.%20In%20addition%20to%20the%20natural%20defenses%20of%20their%20lairs%2C%20powerful%20chromatic%20dragons%20use%20magical%20guardians%2C%20traps%2C%20and%20subservient%20creatures%20to%20protect%20their%20treasures.%3C/p%3E%3Cp%3EQueen%20of%20Evil%20Dragons.%20Tiamat%20the%20Dragon%20Queen%20is%20the%20chief%20deity%20of%20evil%20dragonkind.%20She%20dwells%20on%20Avernus%2C%20the%20first%20layer%20of%20the%20Nine%20Hells.%20As%20a%20lesser%20god%2C%20Tiamat%20has%20the%20power%20to%20grant%20spells%20to%20her%20worshipers%2C%20though%20she%20is%20loath%20to%20share%20her%20power.%20She%20epitomizes%20the%20avarice%20of%20evil%20dragons%2C%20believing%20that%20the%20multiverse%20and%20all%20its%20treasures%20will%20one%20day%20be%20hers%20and%20hers%20alone.%3C/p%3E%3Cp%3ETiamat%20is%20a%20gigantic%20dragon%20whose%20five%20heads%20reflect%20the%20forms%20of%20the%20chromatic%20dragons%20that%20worship%20her-black%2C%20blue%2C%20green%2C%20red%2C%20and%20white.%20She%20is%20a%20terror%20on%20the%20battlefield%2C%20capable%20of%20annihilating%20whole%20armies%20with%20her%20five%20breath%20weapons%2C%20her%20formidable%20spellcasting%2C%20and%20her%20fearsome%20claws.%3C/p%3E%3Cp%3ETiamat%27s%20most%20hated%20enemy%20is%20Bahamut%20the%20Platinum%20Dragon%2C%20with%20whom%20she%20shares%20control%20of%20the%20faith%20of%20dragonkind.%20She%20also%20holds%20a%20special%20enmity%20for%20Asmodeus%2C%20who%20long%20ago%20stripped%20her%20of%20the%20rule%20of%20Avernus%20and%20who%20continues%20to%20curb%20the%20Dragon%20Queen%27s%20power.%3C/p%3E%3C/div%3E%3C/div%3E",
    "gmnotes": "",
    "defaulttoken": "{\"left\":455,\"top\":2555,\"width\":70,\"height\":70,\"imgsrc\":\"https://5etools.com/img/MM/White Dragon Wyrmling.png\",\"page_id\":\"-LDrv4LxIbOkscMDYC0x\",\"layer\":\"objects\",\"name\":\"White Dragon Wyrmling\",\"controlledby\":\"-LDE5BumulahP-dCXX2I\",\"represents\":\"-LEHbc48JHyvR6jIracl\",\"bar1_value\":32,\"bar1_max\":32,\"bar1_link\":\"-LEMsGDTK2PECliyr34x\",\"bar2_value\":10,\"bar2_link\":\"-LEHbc8m-T7lFdiSyUq7\",\"bar3_value\":10,\"bar3_link\":\"-LEHbc9GuvQTZ7KebRLP\",\"aura1_radius\":0.63,\"aura1_color\":\"#05ff00\",\"aura2_radius\":0.034999999999999996,\"aura2_color\":\"#b6d7a8\",\"showname\":true,\"showplayers_name\":true,\"showplayers_aura1\":true,\"showplayers_aura2\":true,\"light_radius\":\"60\",\"light_dimradius\":\"60\",\"light_hassight\":true,\"lastmove\":\"470,2561\"}",
    "tags": "[\"monsters-dragon\",\"monsters-cr-2\",\"monsters-monster-manual\",\"monsters\"]",
    "controlledby": "-LDE5BumulahP-dCXX2I",
    "inplayerjournals": "-LDE5BumulahP-dCXX2I",
    "attribs": [
        {
            "name": "npc",
            "current": 1,
            "max": "",
            "id": "-LEHbc4umMC8g-csATC0"
        },
        {
            "name": "npc_toggle",
            "current": 1,
            "max": "",
            "id": "-LEHbc4umMC8g-csATC1"
        },
        {
            "name": "npc_options-flag",
            "current": "0",
            "max": "",
            "id": "-LEHbc4umMC8g-csATC2"
        },
        {
            "name": "wtype",
            "current": "@{whispertoggle}",
            "max": "",
            "id": "-LEHbc4umMC8g-csATC3"
        },
        {
            "name": "rtype",
            "current": "@{advantagetoggle}",
            "max": "",
            "id": "-LEHbc4wF1dla96dihqf"
        },
        {
            "name": "advantagetoggle",
            "current": "{{query=1}} {{disadvantage=1}} {{r2=[[@{d20}",
            "max": "",
            "id": "-LEHbc4wF1dla96dihqg"
        },
        {
            "name": "whispertoggle",
            "current": "",
            "max": "",
            "id": "-LEHbc4wF1dla96dihqh"
        },
        {
            "name": "dtype",
            "current": "full",
            "max": "",
            "id": "-LEHbc4wF1dla96dihqi"
        },
        {
            "name": "npc_name",
            "current": "Glaephclaw",
            "max": "",
            "id": "-LEHbc4xwo70Vtry6KB4"
        },
        {
            "name": "npc_size",
            "current": "Medium",
            "max": "",
            "id": "-LEHbc4xwo70Vtry6KB5"
        },
        {
            "name": "type",
            "current": "dragon",
            "max": "",
            "id": "-LEHbc4xwo70Vtry6KB6"
        },
        {
            "name": "npc_type",
            "current": "Medium dragon, chaotic evil",
            "max": "",
            "id": "-LEHbc4xwo70Vtry6KB7"
        },
        {
            "name": "npc_alignment",
            "current": "chaotic evil",
            "max": "",
            "id": "-LEHbc4xwo70Vtry6KB8"
        },
        {
            "name": "npc_ac",
            "current": "16",
            "max": "",
            "id": "-LEHbc4xwo70Vtry6KB9"
        },
        {
            "name": "npc_actype",
            "current": "natural armor",
            "max": "",
            "id": "-LEHbc4xwo70Vtry6KBA"
        },
        {
            "name": "npc_hpbase",
            "current": 32,
            "max": "",
            "id": "-LEHbc4xwo70Vtry6KBB"
        },
        {
            "name": "npc_hpformula",
            "current": "5d8+10",
            "max": "",
            "id": "-LEHbc4xwo70Vtry6KBC"
        },
        {
            "name": "npc_speed",
            "current": "30ft., burrow 0ft., fly 60ft., swim 30ft.",
            "max": "",
            "id": "-LEHbc4zkbTRX30-I683"
        },
        {
            "name": "strength",
            "current": 14,
            "max": "",
            "id": "-LEHbc4zkbTRX30-I684"
        },
        {
            "name": "strength_base",
            "current": 14,
            "max": "",
            "id": "-LEHbc5-jSlQKyTReVxv"
        },
        {
            "name": "strength_mod",
            "current": 2,
            "max": "",
            "id": "-LEHbc5-jSlQKyTReVxw"
        },
        {
            "name": "dexterity",
            "current": 10,
            "max": "",
            "id": "-LEHbc5-jSlQKyTReVxx"
        },
        {
            "name": "dexterity_base",
            "current": 10,
            "max": "",
            "id": "-LEHbc5-jSlQKyTReVxy"
        },
        {
            "name": "dexterity_mod",
            "current": 0,
            "max": "",
            "id": "-LEHbc5-jSlQKyTReVxz"
        },
        {
            "name": "constitution",
            "current": 14,
            "max": "",
            "id": "-LEHbc512vy6RwMgoDnd"
        },
        {
            "name": "constitution_base",
            "current": 14,
            "max": "",
            "id": "-LEHbc512vy6RwMgoDne"
        },
        {
            "name": "constitution_mod",
            "current": 2,
            "max": "",
            "id": "-LEHbc512vy6RwMgoDnf"
        },
        {
            "name": "intelligence",
            "current": 5,
            "max": "",
            "id": "-LEHbc512vy6RwMgoDng"
        },
        {
            "name": "intelligence_base",
            "current": 5,
            "max": "",
            "id": "-LEHbc512vy6RwMgoDnh"
        },
        {
            "name": "intelligence_mod",
            "current": -3,
            "max": "",
            "id": "-LEHbc52kri4x6yVage9"
        },
        {
            "name": "wisdom",
            "current": 10,
            "max": "",
            "id": "-LEHbc52kri4x6yVageA"
        },
        {
            "name": "wisdom_base",
            "current": 10,
            "max": "",
            "id": "-LEHbc52kri4x6yVageB"
        },
        {
            "name": "wisdom_mod",
            "current": 0,
            "max": "",
            "id": "-LEHbc52kri4x6yVageC"
        },
        {
            "name": "charisma",
            "current": 11,
            "max": "",
            "id": "-LEHbc52kri4x6yVageD"
        },
        {
            "name": "charisma_base",
            "current": 11,
            "max": "",
            "id": "-LEHbc530Kj5DZw80vN5"
        },
        {
            "name": "charisma_mod",
            "current": 0,
            "max": "",
            "id": "-LEHbc530Kj5DZw80vN6"
        },
        {
            "name": "passive",
            "current": 14,
            "max": "",
            "id": "-LEHbc530Kj5DZw80vN7"
        },
        {
            "name": "npc_languages",
            "current": "Draconic",
            "max": "",
            "id": "-LEHbc530Kj5DZw80vN8"
        },
        {
            "name": "npc_challenge",
            "current": "2",
            "max": "",
            "id": "-LEHbc54k-e4fw7Qav1f"
        },
        {
            "name": "npc_xp",
            "current": "450",
            "max": "",
            "id": "-LEHbc54k-e4fw7Qav1g"
        },
        {
            "name": "npc_vulnerabilities",
            "current": "",
            "max": "",
            "id": "-LEHbc54k-e4fw7Qav1h"
        },
        {
            "name": "damage_vulnerabilities",
            "current": "",
            "max": "",
            "id": "-LEHbc54k-e4fw7Qav1i"
        },
        {
            "name": "npc_resistances",
            "current": "",
            "max": "",
            "id": "-LEHbc54k-e4fw7Qav1j"
        },
        {
            "name": "damage_resistances",
            "current": "",
            "max": "",
            "id": "-LEHbc552S_pl1tt5Miu"
        },
        {
            "name": "npc_immunities",
            "current": "cold",
            "max": "",
            "id": "-LEHbc552S_pl1tt5Miv"
        },
        {
            "name": "damage_immunities",
            "current": "cold",
            "max": "",
            "id": "-LEHbc552S_pl1tt5Miw"
        },
        {
            "name": "npc_condition_immunities",
            "current": "",
            "max": "",
            "id": "-LEHbc552S_pl1tt5Mix"
        },
        {
            "name": "damage_condition_immunities",
            "current": "",
            "max": "",
            "id": "-LEHbc56tgQmqG2pYK9C"
        },
        {
            "name": "npc_senses",
            "current": "blindsight 10 ft., darkvision 60 ft., passive Perception 14",
            "max": "",
            "id": "-LEHbc56tgQmqG2pYK9D"
        },
        {
            "name": "npc_saving_flag",
            "current": "2242",
            "max": "",
            "id": "-LEHbc57FQZd6pht1Cro"
        },
        {
            "name": "npc_dex_save_base",
            "current": "+2",
            "max": "",
            "id": "-LEHbc57FQZd6pht1Crp"
        },
        {
            "name": "dex_saving_throw_proficient",
            "current": "+2",
            "max": "",
            "id": "-LEHbc58jHT1I9YnEC8U"
        },
        {
            "name": "npc_con_save_base",
            "current": "+4",
            "max": "",
            "id": "-LEHbc58jHT1I9YnEC8V"
        },
        {
            "name": "con_saving_throw_proficient",
            "current": "+4",
            "max": "",
            "id": "-LEHbc58jHT1I9YnEC8W"
        },
        {
            "name": "npc_wis_save_base",
            "current": "+2",
            "max": "",
            "id": "-LEHbc58jHT1I9YnEC8X"
        },
        {
            "name": "wis_saving_throw_proficient",
            "current": "+2",
            "max": "",
            "id": "-LEHbc58jHT1I9YnEC8Y"
        },
        {
            "name": "npc_cha_save_base",
            "current": "+2",
            "max": "",
            "id": "-LEHbc58jHT1I9YnEC8Z"
        },
        {
            "name": "cha_saving_throw_proficient",
            "current": "+2",
            "max": "",
            "id": "-LEHbc58jHT1I9YnEC8_"
        },
        {
            "name": "npc_skills_flag",
            "current": "42",
            "max": "",
            "id": "-LEHbc58jHT1I9YnEC8a"
        },
        {
            "name": "npc_skills",
            "current": "Perception +4, Stealth +2",
            "max": "",
            "id": "-LEHbc58jHT1I9YnEC8b"
        },
        {
            "name": "npc_perception_base",
            "current": 4,
            "max": "",
            "id": "-LEHbc59AJ9hnJvLU4JE"
        },
        {
            "name": "npc_perception_base",
            "current": 4,
            "max": "",
            "id": "-LEHbc59AJ9hnJvLU4JF"
        },
        {
            "name": "npc_perception",
            "current": 4,
            "max": "",
            "id": "-LEHbc59AJ9hnJvLU4JG"
        },
        {
            "name": "npc_stealth_base",
            "current": 2,
            "max": "",
            "id": "-LEHbc59AJ9hnJvLU4JH"
        },
        {
            "name": "npc_stealth_base",
            "current": 2,
            "max": "",
            "id": "-LEHbc5AQFJtb0htGtCE"
        },
        {
            "name": "npc_stealth",
            "current": 2,
            "max": "",
            "id": "-LEHbc5AQFJtb0htGtCF"
        },
        {
            "name": "repeating_npcaction_-LEHbc5CyRPDXMZ3DekH_name",
            "current": "Bite",
            "max": "",
            "id": "-LEHbc5EEkeDLWX-u8Vu"
        },
        {
            "name": "repeating_npcaction_-LEHbc5CyRPDXMZ3DekH_attack_flag",
            "current": "on",
            "max": "",
            "id": "-LEHbc5EEkeDLWX-u8Vv"
        },
        {
            "name": "repeating_npcaction_-LEHbc5CyRPDXMZ3DekH_npc_options-flag",
            "current": "0",
            "max": "",
            "id": "-LEHbc5EEkeDLWX-u8Vw"
        },
        {
            "name": "repeating_npcaction_-LEHbc5CyRPDXMZ3DekH_attack_display_flag",
            "current": "{{attack=1}}",
            "max": "",
            "id": "-LEHbc5Fqy3BRozp31HJ"
        },
        {
            "name": "repeating_npcaction_-LEHbc5CyRPDXMZ3DekH_attack_options",
            "current": "{{attack=1}}",
            "max": "",
            "id": "-LEHbc5Fqy3BRozp31HK"
        },
        {
            "name": "repeating_npcaction_-LEHbc5CyRPDXMZ3DekH_attack_tohit",
            "current": "4",
            "max": "",
            "id": "-LEHbc5Fqy3BRozp31HL"
        },
        {
            "name": "repeating_npcaction_-LEHbc5CyRPDXMZ3DekH_attack_damage",
            "current": "1d10+2",
            "max": "",
            "id": "-LEHbc5Fqy3BRozp31HM"
        },
        {
            "name": "repeating_npcaction_-LEHbc5CyRPDXMZ3DekH_attack_crit",
            "current": "1d10",
            "max": "",
            "id": "-LEHbc5Fqy3BRozp31HN"
        },
        {
            "name": "repeating_npcaction_-LEHbc5CyRPDXMZ3DekH_attack_damagetype",
            "current": "piercing",
            "max": "",
            "id": "-LEHbc5HDMShxDrMZoYw"
        },
        {
            "name": "repeating_npcaction_-LEHbc5CyRPDXMZ3DekH_attack_damage2",
            "current": "1d6",
            "max": "",
            "id": "-LEHbc5HDMShxDrMZoYx"
        },
        {
            "name": "repeating_npcaction_-LEHbc5CyRPDXMZ3DekH_attack_crit2",
            "current": "1d6",
            "max": "",
            "id": "-LEHbc5HDMShxDrMZoYy"
        },
        {
            "name": "repeating_npcaction_-LEHbc5CyRPDXMZ3DekH_attack_damagetype2",
            "current": "cold",
            "max": "",
            "id": "-LEHbc5Ig0-Ohp8dFk1P"
        },
        {
            "name": "repeating_npcaction_-LEHbc5CyRPDXMZ3DekH_name_display",
            "current": "Bite",
            "max": "",
            "id": "-LEHbc5Ig0-Ohp8dFk1Q"
        },
        {
            "name": "repeating_npcaction_-LEHbc5CyRPDXMZ3DekH_rollbase",
            "current": "@{wtype}&{template:npcaction} {{attack=1}} @{damage_flag} @{npc_name_flag} {{rname=@{name}}} {{r1=[[@{d20}+(@{attack_tohit}+0)]]}} @{rtype}+(@{attack_tohit}+0)]]}} {{dmg1=[[@{attack_damage}+0]]}} {{dmg1type=@{attack_damagetype}}} {{dmg2=[[@{attack_damage2}+0]]}} {{dmg2type=@{attack_damagetype2}}} {{crit1=[[@{attack_crit}+0]]}} {{crit2=[[@{attack_crit2}+0]]}} {{description=@{show_desc}}} @{charname_output}",
            "max": "",
            "id": "-LEHbc5Ig0-Ohp8dFk1R"
        },
        {
            "name": "repeating_npcaction_-LEHbc5CyRPDXMZ3DekH_attack_type",
            "current": "Melee",
            "max": "",
            "id": "-LEHbc5Ig0-Ohp8dFk1S"
        },
        {
            "name": "repeating_npcaction_-LEHbc5CyRPDXMZ3DekH_attack_type_display",
            "current": "Melee Weapon Attack:",
            "max": "",
            "id": "-LEHbc5Ig0-Ohp8dFk1T"
        },
        {
            "name": "repeating_npcaction_-LEHbc5CyRPDXMZ3DekH_attack_tohitrange",
            "current": "+4, Reach 5 ft.,  one target",
            "max": "",
            "id": "-LEHbc5J_GCrvPhmvCmj"
        },
        {
            "name": "repeating_npcaction_-LEHbc5CyRPDXMZ3DekH_attack_range",
            "current": "5 ft.",
            "max": "",
            "id": "-LEHbc5J_GCrvPhmvCmk"
        },
        {
            "name": "repeating_npcaction_-LEHbc5CyRPDXMZ3DekH_attack_target",
            "current": " one target",
            "max": "",
            "id": "-LEHbc5J_GCrvPhmvCml"
        },
        {
            "name": "repeating_npcaction_-LEHbc5CyRPDXMZ3DekH_damage_flag",
            "current": "{{damage=1}} {{dmg1flag=1}} {{dmg2flag=1}} ",
            "max": "",
            "id": "-LEHbc5J_GCrvPhmvCmm"
        },
        {
            "name": "repeating_npcaction_-LEHbc5CyRPDXMZ3DekH_attack_onhit",
            "current": "7 (1d10+2) piercing damage plus 3 (1d6) cold damage",
            "max": "",
            "id": "-LEHbc5Kb13DdDb0HZvH"
        },
        {
            "name": "repeating_npcaction_-LEHbc5CyRPDXMZ3DekH_description",
            "current": "Hit: 7 (1d10+2) piercing damage plus 2 (1d4) cold damage.",
            "max": "",
            "id": "-LEHbc5Kb13DdDb0HZvI"
        },
        {
            "name": "repeating_npcaction_-LEHbc5CyRPDXMZ3DekH_description_flag",
            "current": 3,
            "max": "",
            "id": "-LEHbc5Kb13DdDb0HZvJ"
        },
        {
            "name": "repeating_npcaction_-LEHbc5LS2vW4yrZDJ8E_name",
            "current": "Cold Breath (Recharge 5—6)",
            "max": "",
            "id": "-LEHbc5LS2vW4yr_DJ8F"
        },
        {
            "name": "repeating_npcaction_-LEHbc5LS2vW4yrZDJ8E_npc_options-flag",
            "current": "0",
            "max": "",
            "id": "-LEHbc5ML54s3BZI2Ahz"
        },
        {
            "name": "repeating_npcaction_-LEHbc5LS2vW4yrZDJ8E_rollbase",
            "current": "@{wtype}&{template:npcaction}  @{damage_flag} @{npc_name_flag} {{rname=@{name}}} {{r1=[[@{d20}+(@{attack_tohit}+0)]]}} @{rtype}+(@{attack_tohit}+0)]]}} {{dmg1=[[@{attack_damage}+0]]}} {{dmg1type=@{attack_damagetype}}} {{dmg2=[[@{attack_damage2}+0]]}} {{dmg2type=@{attack_damagetype2}}} {{crit1=[[@{attack_crit}+0]]}} {{crit2=[[@{attack_crit2}+0]]}} {{description=@{show_desc}}} @{charname_output}",
            "max": "",
            "id": "-LEHbc5ML54s3BZI2Ai-"
        },
        {
            "name": "repeating_npcaction_-LEHbc5LS2vW4yrZDJ8E_name_display",
            "current": "Cold Breath (Recharge 5—6)",
            "max": "",
            "id": "-LEHbc5ML54s3BZI2Ai0"
        },
        {
            "name": "repeating_npcaction_-LEHbc5LS2vW4yrZDJ8E_description",
            "current": "The dragon exhales an icy blast of hail in a 15-foot cone. Each creature in that area must make a DC 12 Constitution saving throw, taking 22 (5d8)([[5d8]]) cold damage on a failed save, or half as much damage on a successful one.\n\n",
            "max": "",
            "id": "-LEHbc5ML54s3BZI2Ai1"
        },
        {
            "name": "repeating_npcaction_-LEHbc5LS2vW4yrZDJ8E_description_flag",
            "current": 4,
            "max": "",
            "id": "-LEHbc5NwhfVAxzTlHxk"
        },
        {
            "name": "global_attack_mod",
            "current": "",
            "max": "",
            "id": "-LEHbc6Ahn6MxsaWgZeq"
        },
        {
            "name": "global_damage_mod",
            "current": 0,
            "max": "",
            "id": "-LEHbc6COiuRsWg3s70T"
        },
        {
            "name": "global_damage_mod_crit",
            "current": "",
            "max": "",
            "id": "-LEHbc6DlJbIUAkXxXe3"
        },
        {
            "name": "spell_attack_bonus",
            "current": "0",
            "max": "",
            "id": "-LEHbc6IQMiiQBNMs8K-"
        },
        {
            "name": "spell_save_dc",
            "current": "0",
            "max": "",
            "id": "-LEHbc6Ljf_hb5ndK5K7"
        },
        {
            "name": "npc_dex_negative",
            "current": 0,
            "max": "",
            "id": "-LEHbc6Qf5k4Tq0I-GAV"
        },
        {
            "name": "hitdietype",
            "current": 6,
            "max": "",
            "id": "-LEHbc6SacCTRwBZoYCt"
        },
        {
            "name": "spellcasting_ability",
            "current": "0*",
            "max": "",
            "id": "-LEHbc6UfyK6HXU4EGza"
        },
        {
            "name": "strength_save_prof",
            "current": 0,
            "max": "",
            "id": "-LEHbc6W-C5pucextZxI"
        },
        {
            "name": "dexterity_save_prof",
            "current": 0,
            "max": "",
            "id": "-LEHbc6YNor7HoxxgQQK"
        },
        {
            "name": "constitution_save_prof",
            "current": 0,
            "max": "",
            "id": "-LEHbc6Z6mFMHmIQ5bjC"
        },
        {
            "name": "intelligence_save_prof",
            "current": 0,
            "max": "",
            "id": "-LEHbc6Z6mFMHmIQ5bjD"
        },
        {
            "name": "wisdom_save_prof",
            "current": 0,
            "max": "",
            "id": "-LEHbc6bjLu2OKhyJfNq"
        },
        {
            "name": "charisma_save_prof",
            "current": 0,
            "max": "",
            "id": "-LEHbc6dLnn2Nzb0i8vz"
        },
        {
            "name": "class_resource_name",
            "current": "",
            "max": "",
            "id": "-LEHbc6gAwVaPR9YKlWf"
        },
        {
            "name": "hitdie_final",
            "current": "@{hitdietype}",
            "max": "",
            "id": "-LEHbc6gAwVaPR9YKlWg"
        },
        {
            "name": "level",
            "current": 1,
            "max": "",
            "id": "-LEHbc6i66oHa_rJOngo"
        },
        {
            "name": "caster_level",
            "current": 0,
            "max": "",
            "id": "-LEHbc6kqN1Qr1VTMW3t"
        },
        {
            "name": "hit_dice",
            "current": "",
            "max": 1,
            "id": "-LEHbc6l9t8kFr-v9bKG"
        },
        {
            "name": "strength_save_bonus",
            "current": 2,
            "max": "",
            "id": "-LEHbc6set_1iExMA7dd"
        },
        {
            "name": "athletics_bonus",
            "current": 2,
            "max": "",
            "id": "-LEHbc6tElFx90yZM0vb"
        },
        {
            "name": "dexterity_save_bonus",
            "current": 0,
            "max": "",
            "id": "-LEHbc6wCFGD1MFlV_PI"
        },
        {
            "name": "acrobatics_bonus",
            "current": 0,
            "max": "",
            "id": "-LEHbc6yomy-jnESZXZF"
        },
        {
            "name": "sleight_of_hand_bonus",
            "current": 0,
            "max": "",
            "id": "-LEHbc6zASrsOhbLaNqD"
        },
        {
            "name": "stealth_bonus",
            "current": 0,
            "max": "",
            "id": "-LEHbc7-BDELyifLCrQG"
        },
        {
            "name": "initiative_bonus",
            "current": 0,
            "max": "",
            "id": "-LEHbc714kwxVRd3FCRo"
        },
        {
            "name": "constitution_save_bonus",
            "current": 2,
            "max": "",
            "id": "-LEHbc7233eApVX_H00X"
        },
        {
            "name": "intelligence_save_bonus",
            "current": -3,
            "max": "",
            "id": "-LEHbc750GeUq7cdGtMd"
        },
        {
            "name": "arcana_bonus",
            "current": -3,
            "max": "",
            "id": "-LEHbc76FC_G_x8aa-i5"
        },
        {
            "name": "history_bonus",
            "current": -3,
            "max": "",
            "id": "-LEHbc780CDoiJSEx1Dh"
        },
        {
            "name": "investigation_bonus",
            "current": -3,
            "max": "",
            "id": "-LEHbc79aFUHahaYVwF8"
        },
        {
            "name": "nature_bonus",
            "current": -3,
            "max": "",
            "id": "-LEHbc7ATBdNn9Bw99c6"
        },
        {
            "name": "religion_bonus",
            "current": -3,
            "max": "",
            "id": "-LEHbc7BTI5pTww8Gl2M"
        },
        {
            "name": "wisdom_save_bonus",
            "current": 0,
            "max": "",
            "id": "-LEHbc7C4zIb-Hl0_DyP"
        },
        {
            "name": "animal_handling_bonus",
            "current": 0,
            "max": "",
            "id": "-LEHbc7D5AB2jE75JPhK"
        },
        {
            "name": "insight_bonus",
            "current": 0,
            "max": "",
            "id": "-LEHbc7G9s8Eu_UFm5YX"
        },
        {
            "name": "medicine_bonus",
            "current": 0,
            "max": "",
            "id": "-LEHbc7HvVIY1Lfcgkj3"
        },
        {
            "name": "perception_bonus",
            "current": 0,
            "max": "",
            "id": "-LEHbc7JFpHsf4VxP6Hc"
        },
        {
            "name": "survival_bonus",
            "current": 0,
            "max": "",
            "id": "-LEHbc7L7Y7_T5bzdY0Z"
        },
        {
            "name": "charisma_save_bonus",
            "current": 0,
            "max": "",
            "id": "-LEHbc7METbcatPw71nV"
        },
        {
            "name": "deception_bonus",
            "current": 0,
            "max": "",
            "id": "-LEHbc7NivJ5g6O7rMep"
        },
        {
            "name": "intimidation_bonus",
            "current": 0,
            "max": "",
            "id": "-LEHbc7P-q9PjMPMxpN7"
        },
        {
            "name": "performance_bonus",
            "current": 0,
            "max": "",
            "id": "-LEHbc7P-q9PjMPMxpN8"
        },
        {
            "name": "persuasion_bonus",
            "current": 0,
            "max": "",
            "id": "-LEHbc7QgjZVDyf1X_EM"
        },
        {
            "name": "armorwarningflag",
            "current": "hide",
            "max": "",
            "id": "-LEHbc8jAJs0CanRJMAm"
        },
        {
            "name": "armorwarning",
            "current": "0",
            "max": "",
            "id": "-LEHbc8kwEui38n5-7HS"
        },
        {
            "name": "ac",
            "current": 10,
            "max": "",
            "id": "-LEHbc8m-T7lFdiSyUq7"
        },
        {
            "name": "lvl1_slots_total",
            "current": 0,
            "max": "",
            "id": "-LEHbc8pBTNVexLP5gAX"
        },
        {
            "name": "lvl2_slots_total",
            "current": 0,
            "max": "",
            "id": "-LEHbc8sCaEVXy9njhmZ"
        },
        {
            "name": "lvl3_slots_total",
            "current": 0,
            "max": "",
            "id": "-LEHbc8sCaEVXy9njhm_"
        },
        {
            "name": "lvl4_slots_total",
            "current": 0,
            "max": "",
            "id": "-LEHbc8uM_kd4ah5UasI"
        },
        {
            "name": "lvl5_slots_total",
            "current": 0,
            "max": "",
            "id": "-LEHbc8w3nQuKW36LDR9"
        },
        {
            "name": "lvl6_slots_total",
            "current": 0,
            "max": "",
            "id": "-LEHbc8xS7n2aJkyj-Gy"
        },
        {
            "name": "lvl7_slots_total",
            "current": 0,
            "max": "",
            "id": "-LEHbc8yln_4Umbfr1Ce"
        },
        {
            "name": "lvl8_slots_total",
            "current": 0,
            "max": "",
            "id": "-LEHbc9-cPbRGo6gQuO2"
        },
        {
            "name": "lvl9_slots_total",
            "current": 0,
            "max": "",
            "id": "-LEHbc90ybOT-c3Tv3LR"
        },
        {
            "name": "pb",
            "current": 2,
            "max": "",
            "id": "-LEHbc90ybOT-c3Tv3LS"
        },
        {
            "name": "jack",
            "current": 1,
            "max": "",
            "id": "-LEHbc93nkGT5ql2SXaq"
        },
        {
            "name": "pbd_safe",
            "current": "",
            "max": "",
            "id": "-LEHbc95tuCoFECe-vpX"
        },
        {
            "name": "passive_wisdom",
            "current": 10,
            "max": "",
            "id": "-LEHbc9GuvQTZ7KebRLP"
        },
        {
            "name": "jack_bonus",
            "current": "",
            "max": "",
            "id": "-LEHbc9X7Xx2-f4HMTTG"
        },
        {
            "name": "jack_attr",
            "current": "",
            "max": "",
            "id": "-LEHbc9X7Xx2-f4HMTTH"
        },
        {
            "name": "death_save_bonus",
            "current": 0,
            "max": "",
            "id": "-LEHbc9t4-kzGdpnzdHi"
        },
        {
            "name": "npc_str_negative",
            "current": 0,
            "max": "",
            "id": "-LEHbcFKM0IQQnSUBzJF"
        },
        {
            "name": "npc_con_negative",
            "current": 0,
            "max": "",
            "id": "-LEHbcFOvMV0fSD9ixmM"
        },
        {
            "name": "npc_int_negative",
            "current": 1,
            "max": "",
            "id": "-LEHbcFRTWGzz_dpbCMX"
        },
        {
            "name": "npc_wis_negative",
            "current": 0,
            "max": "",
            "id": "-LEHbcFSSmpN1pMQicaU"
        },
        {
            "name": "npc_cha_negative",
            "current": 0,
            "max": "",
            "id": "-LEHbcFVIGnFJnUpit99"
        },
        {
            "name": "pb_custom",
            "current": 2,
            "max": "",
            "id": "-LEHbcFYATw-8XLpEhZ0"
        },
        {
            "name": "pb_type",
            "current": "custom",
            "max": "",
            "id": "-LEHbcFYATw-8XLpEhZ1"
        },
        {
            "name": "npc_str_save",
            "current": "",
            "max": "",
            "id": "-LEHbcFa4cm8QmIl_WEj"
        },
        {
            "name": "npc_str_save_flag",
            "current": 0,
            "max": "",
            "id": "-LEHbcFb_XA0Do1M8YCN"
        },
        {
            "name": "npc_dex_save",
            "current": 2,
            "max": "",
            "id": "-LEHbcFb_XA0Do1M8YCO"
        },
        {
            "name": "npc_dex_save_flag",
            "current": 1,
            "max": "",
            "id": "-LEHbcFeIFI0gVndV8go"
        },
        {
            "name": "npc_con_save",
            "current": 4,
            "max": "",
            "id": "-LEHbcFfg8h7p0Sh1U2A"
        },
        {
            "name": "npc_con_save_flag",
            "current": 1,
            "max": "",
            "id": "-LEHbcFgsXt-8wrEW9Yn"
        },
        {
            "name": "npc_int_save",
            "current": "",
            "max": "",
            "id": "-LEHbcFhQWYtZ2f3IeMb"
        },
        {
            "name": "npc_int_save_flag",
            "current": 0,
            "max": "",
            "id": "-LEHbcFijPGC3cNTT200"
        },
        {
            "name": "npc_wis_save",
            "current": 2,
            "max": "",
            "id": "-LEHbcFkG0bIT1ZEu-xz"
        },
        {
            "name": "npc_wis_save_flag",
            "current": 1,
            "max": "",
            "id": "-LEHbcFkG0bIT1ZEu-y-"
        },
        {
            "name": "npc_cha_save",
            "current": 2,
            "max": "",
            "id": "-LEHbcFljFWUiboKOPeX"
        },
        {
            "name": "npc_cha_save_flag",
            "current": 2,
            "max": "",
            "id": "-LEHbcFnPQldS3QR77yS"
        },
        {
            "name": "npc_stealth_flag",
            "current": 2,
            "max": "",
            "id": "-LEHbcFt7xvqlJ20wsP9"
        },
        {
            "name": "npc_survival",
            "current": "",
            "max": "",
            "id": "-LEHbcFujnOWrCLNelkl"
        },
        {
            "name": "npc_acrobatics",
            "current": "",
            "max": "",
            "id": "-LEHbcFujnOWrCLNelkm"
        },
        {
            "name": "npc_acrobatics_flag",
            "current": 0,
            "max": "",
            "id": "-LEHbcFwlPhBAwko4JTO"
        },
        {
            "name": "npc_animal_handling",
            "current": "",
            "max": "",
            "id": "-LEHbcFy0-2iy1vJJr38"
        },
        {
            "name": "npc_animal_handling_flag",
            "current": 0,
            "max": "",
            "id": "-LEHbcFy0-2iy1vJJr39"
        },
        {
            "name": "npc_arcana",
            "current": "",
            "max": "",
            "id": "-LEHbcFzm-cx9zBwIWDx"
        },
        {
            "name": "npc_arcana_flag",
            "current": 0,
            "max": "",
            "id": "-LEHbcFzm-cx9zBwIWDy"
        },
        {
            "name": "npc_athletics",
            "current": "",
            "max": "",
            "id": "-LEHbcG0Zn5iJi71evyD"
        },
        {
            "name": "npc_athletics_flag",
            "current": 0,
            "max": "",
            "id": "-LEHbcG0Zn5iJi71evyE"
        },
        {
            "name": "npc_deception",
            "current": "",
            "max": "",
            "id": "-LEHbcG2uzkL7r_72TQR"
        },
        {
            "name": "npc_deception_flag",
            "current": 0,
            "max": "",
            "id": "-LEHbcG4Fg2MljaWTst7"
        },
        {
            "name": "npc_history",
            "current": "",
            "max": "",
            "id": "-LEHbcG5QpoWLpBaXQ7b"
        },
        {
            "name": "npc_history_flag",
            "current": 0,
            "max": "",
            "id": "-LEHbcG6qpUIPT7icQ3A"
        },
        {
            "name": "npc_insight",
            "current": "",
            "max": "",
            "id": "-LEHbcG6qpUIPT7icQ3B"
        },
        {
            "name": "npc_insight_flag",
            "current": 0,
            "max": "",
            "id": "-LEHbcG81DC026RSmiPs"
        },
        {
            "name": "npc_intimidation",
            "current": "",
            "max": "",
            "id": "-LEHbcG9E8UTKUS3c3MD"
        },
        {
            "name": "npc_intimidation_flag",
            "current": 0,
            "max": "",
            "id": "-LEHbcGA4zyf6BjdETSH"
        },
        {
            "name": "npc_investigation",
            "current": "",
            "max": "",
            "id": "-LEHbcGBHIrEyhrfNkrv"
        },
        {
            "name": "npc_investigation_flag",
            "current": 0,
            "max": "",
            "id": "-LEHbcGCr7ywVV3Oi14I"
        },
        {
            "name": "npc_medicine",
            "current": "",
            "max": "",
            "id": "-LEHbcGDLL4IhRmgKpSO"
        },
        {
            "name": "npc_medicine_flag",
            "current": 0,
            "max": "",
            "id": "-LEHbcGDLL4IhRmgKpSP"
        },
        {
            "name": "npc_nature",
            "current": "",
            "max": "",
            "id": "-LEHbcGF6dPbs7abpdMu"
        },
        {
            "name": "npc_nature_flag",
            "current": 0,
            "max": "",
            "id": "-LEHbcGGcjVV99LvQ05J"
        },
        {
            "name": "npc_perception_flag",
            "current": 1,
            "max": "",
            "id": "-LEHbcGHyB3PWES8urDQ"
        },
        {
            "name": "npc_performance",
            "current": "",
            "max": "",
            "id": "-LEHbcGIVDM6GdDEAw8a"
        },
        {
            "name": "npc_performance_flag",
            "current": 0,
            "max": "",
            "id": "-LEHbcGIVDM6GdDEAw8b"
        },
        {
            "name": "npc_persuasion",
            "current": "",
            "max": "",
            "id": "-LEHbcGJZc_T8PEFMkuC"
        },
        {
            "name": "npc_persuasion_flag",
            "current": 0,
            "max": "",
            "id": "-LEHbcGKKXAYuDnRQeS6"
        },
        {
            "name": "npc_religion",
            "current": "",
            "max": "",
            "id": "-LEHbcGNFTL0eTaRcCCh"
        },
        {
            "name": "npc_religion_flag",
            "current": 0,
            "max": "",
            "id": "-LEHbcGNFTL0eTaRcCCi"
        },
        {
            "name": "npc_sleight_of_hand",
            "current": "",
            "max": "",
            "id": "-LEHbcGOYjWuSMF9jDjT"
        },
        {
            "name": "npc_sleight_of_hand_flag",
            "current": 0,
            "max": "",
            "id": "-LEHbcGQqfr7rZRdBDde"
        },
        {
            "name": "npc_survival_flag",
            "current": 0,
            "max": "",
            "id": "-LEHbcGRyMzNc7eQ5jft"
        },
        {
            "name": "repeating_npcaction_-LEHbc5LS2vW4yrZDJ8E_attack_tohitrange",
            "current": "+0",
            "max": "",
            "id": "-LEHbcI6Hp1d_wiE8bMo"
        },
        {
            "name": "repeating_npcaction_-LEHbc5LS2vW4yrZDJ8E_attack_onhit",
            "current": "",
            "max": "",
            "id": "-LEHbcI9u9-yl5Xku0Xa"
        },
        {
            "name": "repeating_npcaction_-LEHbc5LS2vW4yrZDJ8E_damage_flag",
            "current": "",
            "max": "",
            "id": "-LEHbcIAX7Z9QzYAPcpk"
        },
        {
            "name": "repeating_npcaction_-LEHbc5LS2vW4yrZDJ8E_attack_crit",
            "current": "",
            "max": "",
            "id": "-LEHbcIB-2LOvpkChGh0"
        },
        {
            "name": "repeating_npcaction_-LEHbc5LS2vW4yrZDJ8E_attack_crit2",
            "current": "",
            "max": "",
            "id": "-LEHbcIC8xeQgdUZ3na8"
        },
        {
            "name": "weighttotal",
            "current": 0,
            "max": "",
            "id": "-LEHbcIFXvIsaUI55SlV"
        },
        {
            "name": "encumberance",
            "current": " ",
            "max": "",
            "id": "-LEHbcIHDVBgCsa45s01"
        },
        {
            "name": "strength_flag",
            "current": 0,
            "max": "",
            "id": "-LEHbcINKIkLa86eenRw"
        },
        {
            "name": "dexterity_flag",
            "current": 0,
            "max": "",
            "id": "-LEHbcIPfk6FMBiwDkRs"
        },
        {
            "name": "constitution_flag",
            "current": 0,
            "max": "",
            "id": "-LEHbcIQ4dK9wb-spRK-"
        },
        {
            "name": "intelligence_flag",
            "current": 0,
            "max": "",
            "id": "-LEHbcITJwKSXVS27Mm_"
        },
        {
            "name": "wisdom_flag",
            "current": 0,
            "max": "",
            "id": "-LEHbcIUn3nEtSzyS4Pk"
        },
        {
            "name": "charisma_flag",
            "current": 0,
            "max": "",
            "id": "-LEHbcIXRKwKEqV7Gxju"
        },
        {
            "name": "npcspell_flag",
            "current": 0,
            "max": "",
            "id": "-LEHbeStXc6xMLgYZIHr"
        },
        {
            "name": "missing_info",
            "current": 0,
            "max": "",
            "id": "-LEHbeSv5E08De2Fnreo"
        },
        {
            "name": "USECOLOR",
            "current": "YES",
            "max": "",
            "id": "-LEHm_bRPOfBCOb-lsAb"
        },
        {
            "name": "USEBLOOD",
            "current": "DEFAULT",
            "max": "",
            "id": "-LEHwUHKAgWAxJrD_Z8p"
        },
        {
            "name": "repeating_npcaction_-LEI49Rh8wjidYlQDU--_name",
            "current": "Cold Breath Recharge",
            "max": "",
            "id": "-LEI4CCxzcsjklY3rwFM"
        },
        {
            "name": "repeating_npcaction_-LEI49Rh8wjidYlQDU--_attack_flag",
            "current": "0",
            "max": "",
            "id": "-LEI4GRhifYMCgu36aqp"
        },
        {
            "name": "repeating_npcaction_-LEI49Rh8wjidYlQDU--_attack_tohitrange",
            "current": "+0",
            "max": "",
            "id": "-LEI4GT_VuMHtQqfHfsV"
        },
        {
            "name": "repeating_npcaction_-LEI49Rh8wjidYlQDU--_attack_onhit",
            "current": "3 (1d6) Recharge damage",
            "max": "",
            "id": "-LEI4GTcOCXQ6tJRIFyX"
        },
        {
            "name": "repeating_npcaction_-LEI49Rh8wjidYlQDU--_damage_flag",
            "current": "{{damage=1}} {{dmg1flag=1}} ",
            "max": "",
            "id": "-LEI4GTfY-MWSlqDjaaN"
        },
        {
            "name": "repeating_npcaction_-LEI49Rh8wjidYlQDU--_attack_crit",
            "current": "1d6",
            "max": "",
            "id": "-LEI4GThZcxUa2bV1xOH"
        },
        {
            "name": "repeating_npcaction_-LEI49Rh8wjidYlQDU--_attack_crit2",
            "current": "",
            "max": "",
            "id": "-LEI4GTjZjfFmeLcBZTE"
        },
        {
            "name": "repeating_npcaction_-LEI49Rh8wjidYlQDU--_rollbase",
            "current": "@{wtype}&{template:npcaction}  @{damage_flag} @{npc_name_flag} {{rname=@{name}}} {{r1=[[@{d20}+(@{attack_tohit}+0)]]}} @{rtype}+(@{attack_tohit}+0)]]}} {{dmg1=[[@{attack_damage}+0]]}} {{dmg1type=@{attack_damagetype}}} {{dmg2=[[@{attack_damage2}+0]]}} {{dmg2type=@{attack_damagetype2}}} {{crit1=[[@{attack_crit}+0]]}} {{crit2=[[@{attack_crit2}+0]]}} {{description=@{show_desc}}} @{charname_output}",
            "max": "",
            "id": "-LEI4GTla4fF-UN1PHJI"
        },
        {
            "name": "repeating_npcaction_-LEI49Rh8wjidYlQDU--_attack_damage",
            "current": "1d6",
            "max": "",
            "id": "-LEI4J6Z_PeWe_gJZPuv"
        },
        {
            "name": "repeating_npcaction_-LEI49Rh8wjidYlQDU--_attack_damagetype",
            "current": "Recharge",
            "max": "",
            "id": "-LEI4L4nIA0vv88c46rs"
        },
        {
            "name": "repeating_npcaction_-LEI49Rh8wjidYlQDU--_description",
            "current": "Recharge Breath Weapon (::5-6::)",
            "max": "",
            "id": "-LEI4Nu38zOn216HeFI4"
        },
        {
            "name": "repeating_npcaction_-LEI49Rh8wjidYlQDU--_npc_options-flag",
            "current": "0",
            "max": "",
            "id": "-LEI4NvAcgzSwKVWk7pK"
        },
        {
            "name": "hp",
            "current": "32",
            "max": "32",
            "id": "-LEMsGDTK2PECliyr34x"
        },
        {
            "name": "version",
            "current": "2.7",
            "max": "",
            "id": "-LGogyna_HuUC1Chjsu-"
        },
        {
            "name": "l1mancer_status",
            "current": "completed",
            "max": "",
            "id": "-LGogynmd9KiYW_0POI8"
        },
        {
            "name": "options-class-selection",
            "current": "0",
            "max": "",
            "id": "-LGogynw32wDNzg3coaF"
        },
        {
            "name": "class_display",
            "current": " 1",
            "max": "",
            "id": "-LGogyoG5RrGElmB6W5D"
        },
        {
            "name": "race_display",
            "current": "",
            "max": "",
            "id": "-LGogyoMr1_43Vgmc2pe"
        },
        {
            "name": "global_skill_mod",
            "current": "",
            "max": "",
            "id": "-LOBzut6tIi1uvMVCc5V"
        },
        {
            "name": "global_save_mod",
            "current": "",
            "max": "",
            "id": "-LOBzutO8n3ATuy6-ldI"
        },
        {
            "name": "global_damage_mod_roll",
            "current": "",
            "max": "",
            "id": "-LOBzuzozsJoos-5nUBa"
        },
        {
            "name": "global_damage_mod_type",
            "current": "",
            "max": "",
            "id": "-LOBzv--kj2FtRgCrTrp"
        },
        {
            "name": "customacwarningflag",
            "current": "hide",
            "max": "",
            "id": "-LOBzvRfNILL9D_oR613"
        }
    ],
    "abilities": [
        {
            "name": "0: Bite",
            "description": "",
            "istokenaction": true,
            "action": "%{selected|repeating_npcaction_$0_npc_action}",
            "order": -1
        },
        {
            "name": "1: Cold Breath (Recharge 5—6)",
            "description": "",
            "istokenaction": true,
            "action": "%{selected|repeating_npcaction_$1_npc_action}",
            "order": -1
        }
    ]
}